spam_bot/__init__.py
spam_bot/spam_bot.py
spam_bot-0.0.3.dist-info/LICENSE
spam_bot-0.0.3.dist-info/METADATA
spam_bot-0.0.3.dist-info/WHEEL
spam_bot-0.0.3.dist-info/top_level.txt
spam_bot-0.0.3.dist-info/RECORD
