Metadata-Version: 2.1
Name: spam-bot
Version: 0.0.3
Summary: Spam anything!
Home-page: https://github.com/HirushaPramuditha/spam-bot
Author: Hirusha Pramuditha
Author-email: hirushapramuditha26@gmail.com
License: UNKNOWN
Platform: UNKNOWN
Classifier: Programming Language :: Python :: 3
Classifier: License :: OSI Approved :: MIT License
Classifier: Operating System :: OS Independent
Requires-Python: >=3.6
Requires-Dist: MouseInfo (==0.1.3)
Requires-Dist: Pillow (==8.1.2)
Requires-Dist: PyAutoGUI (==0.9.52)
Requires-Dist: PyGetWindow (==0.0.9)
Requires-Dist: PyMsgBox (==1.0.9)
Requires-Dist: pyperclip (==1.8.2)
Requires-Dist: PyRect (==0.1.4)
Requires-Dist: PyScreeze (==0.1.26)
Requires-Dist: PyTweening (==1.0.3)
